{
  "sheet_id": "hunton-west",
  "pdf_hash": "b8622a4f0ac670eb1e371f0eb442e2b95ffadcfa4f78bafd1702b9b994d82fcf",
  "alignment": {
    "corners": [
      [
        54.32950283354771,
        -1.721502985561007
      ],
      [
        54.32950283354771,
        -1.70955732861746
      ],
      [
        54.32457973175396,
        -1.70955732861746
      ],
      [
        54.32457973175396,
        -1.721502985561007
      ]
    ],
    "center": [
      54.32704128265083,
      -1.7155301570892334
    ],
    "mpp": 0.33154246320673153,
    "zoom": 18
  },
  "houses": {
    "hunton-west-1": {
      "lat": 54.3267244,
      "lng": -1.720275,
      "image_x": 240,
      "image_y": 933
    },
    "hunton-west-2": {
      "lat": 54.3266916,
      "lng": -1.720039,
      "image_x": 287,
      "image_y": 944
    },
    "hunton-west-3": {
      "lat": 54.3266493,
      "lng": -1.7198056,
      "image_x": 332,
      "image_y": 958
    },
    "hunton-west-4": {
      "lat": 54.326654,
      "lng": -1.7195669,
      "image_x": 379,
      "image_y": 957
    },
    "hunton-west-5": {
      "lat": 54.3266415,
      "lng": -1.7192745,
      "image_x": 436,
      "image_y": 961
    },
    "hunton-west-6": {
      "lat": 54.326446,
      "lng": -1.7190117,
      "image_x": 488,
      "image_y": 1026
    },
    "hunton-west-7": {
      "lat": 54.3266446,
      "lng": -1.718899,
      "image_x": 510,
      "image_y": 960
    },
    "hunton-west-8": {
      "lat": 54.3267557,
      "lng": -1.7186227,
      "image_x": 564,
      "image_y": 922
    },
    "hunton-west-9": {
      "lat": 54.3266196,
      "lng": -1.7183411,
      "image_x": 619,
      "image_y": 968
    },
    "hunton-west-10": {
      "lat": 54.3264069,
      "lng": -1.7184833,
      "image_x": 591,
      "image_y": 1040
    },
    "hunton-west-11": {
      "lat": 54.3263725,
      "lng": -1.7181695,
      "image_x": 653,
      "image_y": 1051
    },
    "hunton-west-12": {
      "lat": 54.3263412,
      "lng": -1.7178556,
      "image_x": 714,
      "image_y": 1062
    },
    "hunton-west-13": {
      "lat": 54.3262958,
      "lng": -1.7175847,
      "image_x": 767,
      "image_y": 1077
    },
    "hunton-west-14": {
      "lat": 54.3262348,
      "lng": -1.7167693,
      "image_x": 927,
      "image_y": 1097
    },
    "hunton-west-15": {
      "lat": 54.3263287,
      "lng": -1.7168632,
      "image_x": 908,
      "image_y": 1066
    },
    "hunton-west-16": {
      "lat": 54.326507,
      "lng": -1.7168874,
      "image_x": 904,
      "image_y": 1006
    },
    "hunton-west-17": {
      "lat": 54.3263912,
      "lng": -1.7163482,
      "image_x": 1009,
      "image_y": 1045
    },
    "hunton-west-18": {
      "lat": 54.3265586,
      "lng": -1.7161363,
      "image_x": 1051,
      "image_y": 989
    },
    "hunton-west-19": {
      "lat": 54.3264976,
      "lng": -1.7158842,
      "image_x": 1100,
      "image_y": 1009
    },
    "hunton-west-20": {
      "lat": 54.3264257,
      "lng": -1.7155838,
      "image_x": 1159,
      "image_y": 1033
    },
    "hunton-west-21": {
      "lat": 54.3266665,
      "lng": -1.7157206,
      "image_x": 1132,
      "image_y": 952
    },
    "hunton-west-22": {
      "lat": 54.3267807,
      "lng": -1.7154551,
      "image_x": 1184,
      "image_y": 914
    },
    "hunton-west-23": {
      "lat": 54.3265023,
      "lng": -1.7153424,
      "image_x": 1206,
      "image_y": 1007
    },
    "hunton-west-24": {
      "lat": 54.3265117,
      "lng": -1.7152083,
      "image_x": 1233,
      "image_y": 1004
    },
    "hunton-west-25": {
      "lat": 54.3266212,
      "lng": -1.7150769,
      "image_x": 1258,
      "image_y": 968
    },
    "hunton-west-26": {
      "lat": 54.3266149,
      "lng": -1.7148113,
      "image_x": 1310,
      "image_y": 970
    },
    "hunton-west-27": {
      "lat": 54.3265352,
      "lng": -1.7147362,
      "image_x": 1325,
      "image_y": 996
    },
    "hunton-west-28": {
      "lat": 54.3266055,
      "lng": -1.7145512,
      "image_x": 1361,
      "image_y": 973
    },
    "hunton-west-29": {
      "lat": 54.3266227,
      "lng": -1.7142883,
      "image_x": 1413,
      "image_y": 967
    },
    "hunton-west-30": {
      "lat": 54.3265711,
      "lng": -1.7139745,
      "image_x": 1474,
      "image_y": 984
    },
    "hunton-west-31": {
      "lat": 54.3265836,
      "lng": -1.7137787,
      "image_x": 1512,
      "image_y": 980
    },
    "hunton-west-32": {
      "lat": 54.3265789,
      "lng": -1.7136446,
      "image_x": 1539,
      "image_y": 982
    },
    "hunton-west-33": {
      "lat": 54.3265993,
      "lng": -1.713497,
      "image_x": 1568,
      "image_y": 975
    },
    "hunton-west-34": {
      "lat": 54.3266446,
      "lng": -1.7132208,
      "image_x": 1622,
      "image_y": 960
    },
    "hunton-west-35": {
      "lat": 54.3266712,
      "lng": -1.7130652,
      "image_x": 1652,
      "image_y": 951
    },
    "hunton-west-36": {
      "lat": 54.32669,
      "lng": -1.7129686,
      "image_x": 1671,
      "image_y": 944
    },
    "hunton-west-37": {
      "lat": 54.3266806,
      "lng": -1.7128801,
      "image_x": 1688,
      "image_y": 948
    },
    "hunton-west-38": {
      "lat": 54.3266681,
      "lng": -1.7127272,
      "image_x": 1718,
      "image_y": 952
    },
    "hunton-west-39": {
      "lat": 54.3266931,
      "lng": -1.7125234,
      "image_x": 1758,
      "image_y": 943
    },
    "hunton-west-40": {
      "lat": 54.3257609,
      "lng": -1.71262,
      "image_x": 1739,
      "image_y": 1256
    },
    "hunton-west-41": {
      "lat": 54.3251164,
      "lng": -1.7130357,
      "image_x": 1658,
      "image_y": 1473
    },
    "hunton-west-42": {
      "lat": 54.3255059,
      "lng": -1.7139584,
      "image_x": 1477,
      "image_y": 1342
    },
    "hunton-west-43": {
      "lat": 54.3257405,
      "lng": -1.7149347,
      "image_x": 1286,
      "image_y": 1263
    }
  }
}